{"config":{"output_file":null,"full_docs":false,"pub_only":false,"reachable_only":false,"distro_crate":false,"signatures":false,"borrow_data":false},"version":"0.19.1","compilation":{"directory":"c:\\Users\\milla\\Desktop\\coding\\Othello\\othello","program":"C:\\Users\\milla\\.rustup\\toolchains\\stable-x86_64-pc-windows-msvc\\bin\\rls.exe","arguments":[],"output":"c:\\Users\\milla\\Desktop\\coding\\Othello\\othello\\target\\rls\\debug\\deps\\libothello-9482efffadccc4a1.rmeta"},"prelude":{"crate_id":{"name":"othello","disambiguator":[10314965780809299811,0]},"crate_root":"src","external_crates":[{"file_name":"c:\\Users\\milla\\Desktop\\coding\\Othello\\othello\\src\\main.rs","num":1,"id":{"name":"std","disambiguator":[7379719041391505039,0]}},{"file_name":"c:\\Users\\milla\\Desktop\\coding\\Othello\\othello\\src\\main.rs","num":2,"id":{"name":"core","disambiguator":[5226548339696486402,0]}},{"file_name":"c:\\Users\\milla\\Desktop\\coding\\Othello\\othello\\src\\main.rs","num":3,"id":{"name":"compiler_builtins","disambiguator":[15782588708828798436,0]}},{"file_name":"c:\\Users\\milla\\Desktop\\coding\\Othello\\othello\\src\\main.rs","num":4,"id":{"name":"rustc_std_workspace_core","disambiguator":[11258588358156983047,0]}},{"file_name":"c:\\Users\\milla\\Desktop\\coding\\Othello\\othello\\src\\main.rs","num":5,"id":{"name":"alloc","disambiguator":[6811839233127289238,0]}},{"file_name":"c:\\Users\\milla\\Desktop\\coding\\Othello\\othello\\src\\main.rs","num":6,"id":{"name":"libc","disambiguator":[6798478037195512723,0]}},{"file_name":"c:\\Users\\milla\\Desktop\\coding\\Othello\\othello\\src\\main.rs","num":7,"id":{"name":"unwind","disambiguator":[12572258325454906649,0]}},{"file_name":"c:\\Users\\milla\\Desktop\\coding\\Othello\\othello\\src\\main.rs","num":8,"id":{"name":"cfg_if","disambiguator":[598470195457823820,0]}},{"file_name":"c:\\Users\\milla\\Desktop\\coding\\Othello\\othello\\src\\main.rs","num":9,"id":{"name":"hashbrown","disambiguator":[7285820039251336650,0]}},{"file_name":"c:\\Users\\milla\\Desktop\\coding\\Othello\\othello\\src\\main.rs","num":10,"id":{"name":"rustc_std_workspace_alloc","disambiguator":[15004074270013699283,0]}},{"file_name":"c:\\Users\\milla\\Desktop\\coding\\Othello\\othello\\src\\main.rs","num":11,"id":{"name":"std_detect","disambiguator":[6568562326383462027,0]}},{"file_name":"c:\\Users\\milla\\Desktop\\coding\\Othello\\othello\\src\\main.rs","num":12,"id":{"name":"rustc_demangle","disambiguator":[7532148157145861684,0]}},{"file_name":"c:\\Users\\milla\\Desktop\\coding\\Othello\\othello\\src\\main.rs","num":13,"id":{"name":"panic_unwind","disambiguator":[15660406440960571571,0]}}],"span":{"file_name":"src\\main.rs","byte_start":0,"byte_end":6877,"line_start":1,"line_end":248,"column_start":1,"column_end":2}},"imports":[{"kind":"GlobUse","ref_id":null,"span":{"file_name":"src\\main.rs","byte_start":22,"byte_end":23,"line_start":1,"line_end":1,"column_start":23,"column_end":24},"alias_span":null,"name":"*","value":"BufRead, Write","parent":{"krate":0,"index":0}}],"defs":[{"kind":"Mod","id":{"krate":0,"index":0},"span":{"file_name":"src\\main.rs","byte_start":0,"byte_end":6877,"line_start":1,"line_end":248,"column_start":1,"column_end":2},"name":"","qualname":"::","value":"src\\main.rs","parent":null,"children":[{"krate":0,"index":1},{"krate":0,"index":2},{"krate":0,"index":3},{"krate":0,"index":45},{"krate":0,"index":52},{"krate":0,"index":53},{"krate":0,"index":55},{"krate":0,"index":56},{"krate":0,"index":4},{"krate":0,"index":7},{"krate":0,"index":8},{"krate":0,"index":13},{"krate":0,"index":19},{"krate":0,"index":23},{"krate":0,"index":29},{"krate":0,"index":36},{"krate":0,"index":40},{"krate":0,"index":44}],"decl_id":null,"docs":"","sig":null,"attributes":[]},{"kind":"TupleVariant","id":{"krate":0,"index":46},"span":{"file_name":"src\\main.rs","byte_start":76,"byte_end":81,"line_start":5,"line_end":5,"column_start":5,"column_end":10},"name":"Empty","qualname":"::Spot::Empty","value":"Spot::Empty","parent":{"krate":0,"index":45},"children":[],"decl_id":null,"docs":"","sig":null,"attributes":[]},{"kind":"TupleVariant","id":{"krate":0,"index":48},"span":{"file_name":"src\\main.rs","byte_start":87,"byte_end":92,"line_start":6,"line_end":6,"column_start":5,"column_end":10},"name":"Black","qualname":"::Spot::Black","value":"Spot::Black","parent":{"krate":0,"index":45},"children":[],"decl_id":null,"docs":"","sig":null,"attributes":[]},{"kind":"TupleVariant","id":{"krate":0,"index":50},"span":{"file_name":"src\\main.rs","byte_start":98,"byte_end":103,"line_start":7,"line_end":7,"column_start":5,"column_end":10},"name":"White","qualname":"::Spot::White","value":"Spot::White","parent":{"krate":0,"index":45},"children":[],"decl_id":null,"docs":"","sig":null,"attributes":[]},{"kind":"Enum","id":{"krate":0,"index":45},"span":{"file_name":"src\\main.rs","byte_start":65,"byte_end":69,"line_start":4,"line_end":4,"column_start":6,"column_end":10},"name":"Spot","qualname":"::Spot","value":"enum Spot { Empty, Black, White, }","parent":null,"children":[{"krate":0,"index":46},{"krate":0,"index":48},{"krate":0,"index":50}],"decl_id":null,"docs":"","sig":null,"attributes":[]},{"kind":"Local","id":{"krate":0,"index":1073741829},"span":{"file_name":"src\\main.rs","byte_start":136,"byte_end":140,"line_start":10,"line_end":10,"column_start":18,"column_end":22},"name":"self","qualname":"<Spot>::to_string::self","value":"Spot","parent":null,"children":[],"decl_id":null,"docs":"","sig":null,"attributes":[]},{"kind":"Method","id":{"krate":0,"index":5},"span":{"file_name":"src\\main.rs","byte_start":126,"byte_end":135,"line_start":10,"line_end":10,"column_start":8,"column_end":17},"name":"to_string","qualname":"<Spot>::to_string","value":"fn to_string(Self) -> &'static str","parent":null,"children":[],"decl_id":null,"docs":"","sig":null,"attributes":[]},{"kind":"Local","id":{"krate":0,"index":1073741830},"span":{"file_name":"src\\main.rs","byte_start":309,"byte_end":313,"line_start":17,"line_end":17,"column_start":17,"column_end":21},"name":"self","qualname":"<Spot>::get_flip::self","value":"Spot","parent":null,"children":[],"decl_id":null,"docs":"","sig":null,"attributes":[]},{"kind":"Method","id":{"krate":0,"index":6},"span":{"file_name":"src\\main.rs","byte_start":300,"byte_end":308,"line_start":17,"line_end":17,"column_start":8,"column_end":16},"name":"get_flip","qualname":"<Spot>::get_flip","value":"fn get_flip(Self) -> Spot","parent":null,"children":[],"decl_id":null,"docs":"","sig":null,"attributes":[]},{"kind":"Function","id":{"krate":0,"index":7},"span":{"file_name":"src\\main.rs","byte_start":488,"byte_end":500,"line_start":26,"line_end":26,"column_start":4,"column_end":16},"name":"clear_screen","qualname":"::clear_screen","value":"fn clear_screen()","parent":null,"children":[],"decl_id":null,"docs":"","sig":null,"attributes":[]},{"kind":"Function","id":{"krate":0,"index":8},"span":{"file_name":"src\\main.rs","byte_start":543,"byte_end":555,"line_start":30,"line_end":30,"column_start":4,"column_end":16},"name":"create_board","qualname":"::create_board","value":"fn create_board() -> [[Spot; ]; ]","parent":null,"children":[],"decl_id":null,"docs":"","sig":null,"attributes":[]},{"kind":"Local","id":{"krate":0,"index":805306376},"span":{"file_name":"src\\main.rs","byte_start":590,"byte_end":595,"line_start":31,"line_end":31,"column_start":13,"column_end":18},"name":"board","qualname":"board$HirId { owner: DefId(0:8 ~ othello[8f26]::create_board), local_id: 12 }","value":"[[Spot; 8]; 8]","parent":null,"children":[],"decl_id":null,"docs":"","sig":null,"attributes":[]},{"kind":"Local","id":{"krate":0,"index":1073741837},"span":{"file_name":"src\\main.rs","byte_start":772,"byte_end":777,"line_start":39,"line_end":39,"column_start":15,"column_end":20},"name":"board","qualname":"::print_game::board","value":"[[Spot; 8]; 8]","parent":null,"children":[],"decl_id":null,"docs":"","sig":null,"attributes":[]},{"kind":"Local","id":{"krate":0,"index":536870925},"span":{"file_name":"src\\main.rs","byte_start":795,"byte_end":806,"line_start":39,"line_end":39,"column_start":38,"column_end":49},"name":"valid_moves","qualname":"::print_game::valid_moves","value":"[[bool; 8]; 8]","parent":null,"children":[],"decl_id":null,"docs":"","sig":null,"attributes":[]},{"kind":"Local","id":{"krate":0,"index":1610612749},"span":{"file_name":"src\\main.rs","byte_start":824,"byte_end":836,"line_start":39,"line_end":39,"column_start":67,"column_end":79},"name":"current_turn","qualname":"::print_game::current_turn","value":"Spot","parent":null,"children":[],"decl_id":null,"docs":"","sig":null,"attributes":[]},{"kind":"Function","id":{"krate":0,"index":13},"span":{"file_name":"src\\main.rs","byte_start":761,"byte_end":771,"line_start":39,"line_end":39,"column_start":4,"column_end":14},"name":"print_game","qualname":"::print_game","value":"fn print_game([[Spot; ]; ], [[bool; ]; ], Spot)","parent":null,"children":[],"decl_id":null,"docs":"","sig":null,"attributes":[]},{"kind":"Local","id":{"krate":0,"index":3623878669},"span":{"file_name":"src\\main.rs","byte_start":879,"byte_end":895,"line_start":42,"line_end":42,"column_start":13,"column_end":29},"name":"valid_moves_text","qualname":"valid_moves_text$HirId { owner: DefId(0:13 ~ othello[8f26]::print_game), local_id: 27 }","value":"std::vec::Vec<[usize; 2]>","parent":null,"children":[],"decl_id":null,"docs":"","sig":null,"attributes":[]},{"kind":"Local","id":{"krate":0,"index":2986344461},"span":{"file_name":"src\\main.rs","byte_start":1014,"byte_end":1015,"line_start":46,"line_end":46,"column_start":9,"column_end":10},"name":"y","qualname":"y$HirId { owner: DefId(0:13 ~ othello[8f26]::print_game), local_id: 77 }","value":"usize","parent":null,"children":[],"decl_id":null,"docs":"","sig":null,"attributes":[]},{"kind":"Local","id":{"krate":0,"index":1577058317},"span":{"file_name":"src\\main.rs","byte_start":1071,"byte_end":1072,"line_start":48,"line_end":48,"column_start":13,"column_end":14},"name":"x","qualname":"x$HirId { owner: DefId(0:13 ~ othello[8f26]::print_game), local_id: 122 }","value":"usize","parent":null,"children":[],"decl_id":null,"docs":"","sig":null,"attributes":[]},{"kind":"Local","id":{"krate":0,"index":612368397},"span":{"file_name":"src\\main.rs","byte_start":1533,"byte_end":1544,"line_start":64,"line_end":64,"column_start":13,"column_end":24},"name":"black_total","qualname":"black_total$HirId { owner: DefId(0:13 ~ othello[8f26]::print_game), local_id: 292 }","value":"i32","parent":null,"children":[],"decl_id":null,"docs":"","sig":null,"attributes":[]},{"kind":"Local","id":{"krate":0,"index":343932941},"span":{"file_name":"src\\main.rs","byte_start":1562,"byte_end":1573,"line_start":65,"line_end":65,"column_start":13,"column_end":24},"name":"white_total","qualname":"white_total$HirId { owner: DefId(0:13 ~ othello[8f26]::print_game), local_id: 296 }","value":"i32","parent":null,"children":[],"decl_id":null,"docs":"","sig":null,"attributes":[]},{"kind":"Local","id":{"krate":0,"index":3028287501},"span":{"file_name":"src\\main.rs","byte_start":1587,"byte_end":1590,"line_start":66,"line_end":66,"column_start":9,"column_end":12},"name":"row","qualname":"row$HirId { owner: DefId(0:13 ~ othello[8f26]::print_game), local_id: 301 }","value":"&[Spot; 8]","parent":null,"children":[],"decl_id":null,"docs":"","sig":null,"attributes":[]},{"kind":"Local","id":{"krate":0,"index":478150669},"span":{"file_name":"src\\main.rs","byte_start":1621,"byte_end":1625,"line_start":67,"line_end":67,"column_start":13,"column_end":17},"name":"spot","qualname":"spot$HirId { owner: DefId(0:13 ~ othello[8f26]::print_game), local_id: 312 }","value":"&Spot","parent":null,"children":[],"decl_id":null,"docs":"","sig":null,"attributes":[]},{"kind":"Local","id":{"krate":0,"index":2139095053},"span":{"file_name":"src\\main.rs","byte_start":2196,"byte_end":2197,"line_start":84,"line_end":84,"column_start":14,"column_end":15},"name":"i","qualname":"i$HirId { owner: DefId(0:13 ~ othello[8f26]::print_game), local_id: 510 }","value":"usize","parent":null,"children":[],"decl_id":null,"docs":"","sig":null,"attributes":[]},{"kind":"Local","id":{"krate":0,"index":4286578701},"span":{"file_name":"src\\main.rs","byte_start":2199,"byte_end":2202,"line_start":84,"line_end":84,"column_start":17,"column_end":20},"name":"pos","qualname":"pos$HirId { owner: DefId(0:13 ~ othello[8f26]::print_game), local_id: 511 }","value":"&[usize; 2]","parent":null,"children":[],"decl_id":null,"docs":"","sig":null,"attributes":[]},{"kind":"Local","id":{"krate":0,"index":1073741843},"span":{"file_name":"src\\main.rs","byte_start":2524,"byte_end":2535,"line_start":97,"line_end":97,"column_start":17,"column_end":28},"name":"valid_moves","qualname":"::invalid_move::valid_moves","value":"[[bool; 8]; 8]","parent":null,"children":[],"decl_id":null,"docs":"","sig":null,"attributes":[]},{"kind":"Local","id":{"krate":0,"index":536870931},"span":{"file_name":"src\\main.rs","byte_start":2553,"byte_end":2560,"line_start":97,"line_end":97,"column_start":46,"column_end":53},"name":"message","qualname":"::invalid_move::message","value":"&str","parent":null,"children":[],"decl_id":null,"docs":"","sig":null,"attributes":[]},{"kind":"Function","id":{"krate":0,"index":19},"span":{"file_name":"src\\main.rs","byte_start":2511,"byte_end":2523,"line_start":97,"line_end":97,"column_start":4,"column_end":16},"name":"invalid_move","qualname":"::invalid_move","value":"fn invalid_move([[bool; ]; ], &'static str) -> [usize; ]","parent":null,"children":[],"decl_id":null,"docs":"","sig":null,"attributes":[]},{"kind":"Local","id":{"krate":0,"index":1073741847},"span":{"file_name":"src\\main.rs","byte_start":2664,"byte_end":2675,"line_start":102,"line_end":102,"column_start":14,"column_end":25},"name":"valid_moves","qualname":"::get_input::valid_moves","value":"[[bool; 8]; 8]","parent":null,"children":[],"decl_id":null,"docs":"","sig":null,"attributes":[]},{"kind":"Function","id":{"krate":0,"index":23},"span":{"file_name":"src\\main.rs","byte_start":2654,"byte_end":2663,"line_start":102,"line_end":102,"column_start":4,"column_end":13},"name":"get_input","qualname":"::get_input","value":"fn get_input([[bool; ]; ]) -> [usize; ]","parent":null,"children":[],"decl_id":null,"docs":"","sig":null,"attributes":[]},{"kind":"Local","id":{"krate":0,"index":3825205271},"span":{"file_name":"src\\main.rs","byte_start":2807,"byte_end":2812,"line_start":106,"line_end":106,"column_start":13,"column_end":18},"name":"input","qualname":"input$HirId { owner: DefId(0:23 ~ othello[8f26]::get_input), local_id: 39 }","value":"std::string::String","parent":null,"children":[],"decl_id":null,"docs":"","sig":null,"attributes":[]},{"kind":"Local","id":{"krate":0,"index":4227858455},"span":{"file_name":"src\\main.rs","byte_start":2930,"byte_end":2942,"line_start":110,"line_end":110,"column_start":9,"column_end":21},"name":"string_parts","qualname":"string_parts$HirId { owner: DefId(0:23 ~ othello[8f26]::get_input), local_id: 63 }","value":"std::str::Split<char>","parent":null,"children":[],"decl_id":null,"docs":"","sig":null,"attributes":[]},{"kind":"Local","id":{"krate":0,"index":3254779927},"span":{"file_name":"src\\main.rs","byte_start":2983,"byte_end":2988,"line_start":112,"line_end":112,"column_start":13,"column_end":18},"name":"count","qualname":"count$HirId { owner: DefId(0:23 ~ othello[8f26]::get_input), local_id: 67 }","value":"usize","parent":null,"children":[],"decl_id":null,"docs":"","sig":null,"attributes":[]},{"kind":"Local","id":{"krate":0,"index":4060086295},"span":{"file_name":"src\\main.rs","byte_start":3006,"byte_end":3009,"line_start":113,"line_end":113,"column_start":13,"column_end":16},"name":"pos","qualname":"pos$HirId { owner: DefId(0:23 ~ othello[8f26]::get_input), local_id: 79 }","value":"[usize; 2]","parent":null,"children":[],"decl_id":null,"docs":"","sig":null,"attributes":[]},{"kind":"Local","id":{"krate":0,"index":1241514007},"span":{"file_name":"src\\main.rs","byte_start":3040,"byte_end":3041,"line_start":114,"line_end":114,"column_start":9,"column_end":10},"name":"c","qualname":"c$HirId { owner: DefId(0:23 ~ othello[8f26]::get_input), local_id: 82 }","value":"&str","parent":null,"children":[],"decl_id":null,"docs":"","sig":null,"attributes":[]},{"kind":"Local","id":{"krate":0,"index":553648151},"span":{"file_name":"src\\main.rs","byte_start":3378,"byte_end":3381,"line_start":123,"line_end":123,"column_start":13,"column_end":16},"name":"num","qualname":"num$HirId { owner: DefId(0:23 ~ othello[8f26]::get_input), local_id: 132 }","value":"std::result::Result<usize, std::num::ParseIntError>","parent":null,"children":[],"decl_id":null,"docs":"","sig":null,"attributes":[]},{"kind":"Local","id":{"krate":0,"index":285212695},"span":{"file_name":"src\\main.rs","byte_start":3439,"byte_end":3440,"line_start":125,"line_end":125,"column_start":16,"column_end":17},"name":"n","qualname":"n$HirId { owner: DefId(0:23 ~ othello[8f26]::get_input), local_id: 136 }","value":"usize","parent":null,"children":[],"decl_id":null,"docs":"","sig":null,"attributes":[]},{"kind":"Local","id":{"krate":0,"index":1073741853},"span":{"file_name":"src\\main.rs","byte_start":4073,"byte_end":4078,"line_start":147,"line_end":147,"column_start":21,"column_end":26},"name":"board","qualname":"::find_valid_moves::board","value":"[[Spot; 8]; 8]","parent":null,"children":[],"decl_id":null,"docs":"","sig":null,"attributes":[]},{"kind":"Local","id":{"krate":0,"index":536870941},"span":{"file_name":"src\\main.rs","byte_start":4096,"byte_end":4108,"line_start":147,"line_end":147,"column_start":44,"column_end":56},"name":"current_turn","qualname":"::find_valid_moves::current_turn","value":"Spot","parent":null,"children":[],"decl_id":null,"docs":"","sig":null,"attributes":[]},{"kind":"Function","id":{"krate":0,"index":29},"span":{"file_name":"src\\main.rs","byte_start":4056,"byte_end":4072,"line_start":147,"line_end":147,"column_start":4,"column_end":20},"name":"find_valid_moves","qualname":"::find_valid_moves","value":"fn find_valid_moves([[Spot; ]; ], Spot) -> [[bool; ]; ]","parent":null,"children":[],"decl_id":null,"docs":"","sig":null,"attributes":[]},{"kind":"Local","id":{"krate":0,"index":1879048221},"span":{"file_name":"src\\main.rs","byte_start":4148,"byte_end":4159,"line_start":148,"line_end":148,"column_start":13,"column_end":24},"name":"valid_moves","qualname":"valid_moves$HirId { owner: DefId(0:29 ~ othello[8f26]::find_valid_moves), local_id: 14 }","value":"[[bool; 8]; 8]","parent":null,"children":[],"decl_id":null,"docs":"","sig":null,"attributes":[]},{"kind":"Local","id":{"krate":0,"index":671088669},"span":{"file_name":"src\\main.rs","byte_start":4187,"byte_end":4188,"line_start":149,"line_end":149,"column_start":9,"column_end":10},"name":"y","qualname":"y$HirId { owner: DefId(0:29 ~ othello[8f26]::find_valid_moves), local_id: 20 }","value":"usize","parent":null,"children":[],"decl_id":null,"docs":"","sig":null,"attributes":[]},{"kind":"Local","id":{"krate":0,"index":67108893},"span":{"file_name":"src\\main.rs","byte_start":4211,"byte_end":4212,"line_start":150,"line_end":150,"column_start":13,"column_end":14},"name":"x","qualname":"x$HirId { owner: DefId(0:29 ~ othello[8f26]::find_valid_moves), local_id: 32 }","value":"usize","parent":null,"children":[],"decl_id":null,"docs":"","sig":null,"attributes":[]},{"kind":"Local","id":{"krate":0,"index":1073741860},"span":{"file_name":"src\\main.rs","byte_start":4385,"byte_end":4390,"line_start":159,"line_end":159,"column_start":15,"column_end":20},"name":"board","qualname":"::valid_move::board","value":"[[Spot; 8]; 8]","parent":null,"children":[],"decl_id":null,"docs":"","sig":null,"attributes":[]},{"kind":"Local","id":{"krate":0,"index":536870948},"span":{"file_name":"src\\main.rs","byte_start":4408,"byte_end":4411,"line_start":159,"line_end":159,"column_start":38,"column_end":41},"name":"pos","qualname":"::valid_move::pos","value":"[usize; 2]","parent":null,"children":[],"decl_id":null,"docs":"","sig":null,"attributes":[]},{"kind":"Local","id":{"krate":0,"index":1610612772},"span":{"file_name":"src\\main.rs","byte_start":4425,"byte_end":4437,"line_start":159,"line_end":159,"column_start":55,"column_end":67},"name":"current_turn","qualname":"::valid_move::current_turn","value":"Spot","parent":null,"children":[],"decl_id":null,"docs":"","sig":null,"attributes":[]},{"kind":"Function","id":{"krate":0,"index":36},"span":{"file_name":"src\\main.rs","byte_start":4374,"byte_end":4384,"line_start":159,"line_end":159,"column_start":4,"column_end":14},"name":"valid_move","qualname":"::valid_move","value":"fn valid_move([[Spot; ]; ], [usize; ], Spot) -> bool","parent":null,"children":[],"decl_id":null,"docs":"","sig":null,"attributes":[]},{"kind":"Local","id":{"krate":0,"index":33554468},"span":{"file_name":"src\\main.rs","byte_start":4538,"byte_end":4542,"line_start":164,"line_end":164,"column_start":9,"column_end":13},"name":"dirs","qualname":"dirs$HirId { owner: DefId(0:36 ~ othello[8f26]::valid_move), local_id: 64 }","value":"[[i32; 2]; 8]","parent":null,"children":[],"decl_id":null,"docs":"","sig":null,"attributes":[]},{"kind":"Local","id":{"krate":0,"index":2717909028},"span":{"file_name":"src\\main.rs","byte_start":4696,"byte_end":4699,"line_start":174,"line_end":174,"column_start":9,"column_end":12},"name":"dir","qualname":"dir$HirId { owner: DefId(0:36 ~ othello[8f26]::valid_move), local_id: 69 }","value":"&[i32; 2]","parent":null,"children":[],"decl_id":null,"docs":"","sig":null,"attributes":[]},{"kind":"Local","id":{"krate":0,"index":4060086308},"span":{"file_name":"src\\main.rs","byte_start":4733,"byte_end":4737,"line_start":175,"line_end":175,"column_start":17,"column_end":21},"name":"dist","qualname":"dist$HirId { owner: DefId(0:36 ~ othello[8f26]::valid_move), local_id: 79 }","value":"i32","parent":null,"children":[],"decl_id":null,"docs":"","sig":null,"attributes":[]},{"kind":"Local","id":{"krate":0,"index":2248146980},"span":{"file_name":"src\\main.rs","byte_start":4774,"byte_end":4775,"line_start":177,"line_end":177,"column_start":17,"column_end":18},"name":"x","qualname":"x$HirId { owner: DefId(0:36 ~ othello[8f26]::valid_move), local_id: 97 }","value":"i32","parent":null,"children":[],"decl_id":null,"docs":"","sig":null,"attributes":[]},{"kind":"Local","id":{"krate":0,"index":3456106532},"span":{"file_name":"src\\main.rs","byte_start":4825,"byte_end":4826,"line_start":178,"line_end":178,"column_start":17,"column_end":18},"name":"y","qualname":"y$HirId { owner: DefId(0:36 ~ othello[8f26]::valid_move), local_id: 115 }","value":"i32","parent":null,"children":[],"decl_id":null,"docs":"","sig":null,"attributes":[]},{"kind":"Local","id":{"krate":0,"index":1073741864},"span":{"file_name":"src\\main.rs","byte_start":5310,"byte_end":5315,"line_start":194,"line_end":194,"column_start":16,"column_end":21},"name":"board","qualname":"::place_piece::board","value":"&mut [[Spot; 8]; 8]","parent":null,"children":[],"decl_id":null,"docs":"","sig":null,"attributes":[]},{"kind":"Local","id":{"krate":0,"index":536870952},"span":{"file_name":"src\\main.rs","byte_start":5338,"byte_end":5341,"line_start":194,"line_end":194,"column_start":44,"column_end":47},"name":"pos","qualname":"::place_piece::pos","value":"[usize; 2]","parent":null,"children":[],"decl_id":null,"docs":"","sig":null,"attributes":[]},{"kind":"Local","id":{"krate":0,"index":1610612776},"span":{"file_name":"src\\main.rs","byte_start":5355,"byte_end":5367,"line_start":194,"line_end":194,"column_start":61,"column_end":73},"name":"current_turn","qualname":"::place_piece::current_turn","value":"Spot","parent":null,"children":[],"decl_id":null,"docs":"","sig":null,"attributes":[]},{"kind":"Function","id":{"krate":0,"index":40},"span":{"file_name":"src\\main.rs","byte_start":5298,"byte_end":5309,"line_start":194,"line_end":194,"column_start":4,"column_end":15},"name":"place_piece","qualname":"::place_piece","value":"fn place_piece(&mut [[Spot; ]; ], [usize; ], Spot)","parent":null,"children":[],"decl_id":null,"docs":"","sig":null,"attributes":[]},{"kind":"Local","id":{"krate":0,"index":469762088},"span":{"file_name":"src\\main.rs","byte_start":5453,"byte_end":5457,"line_start":197,"line_end":197,"column_start":9,"column_end":13},"name":"dirs","qualname":"dirs$HirId { owner: DefId(0:40 ~ othello[8f26]::place_piece), local_id: 56 }","value":"[[i32; 2]; 8]","parent":null,"children":[],"decl_id":null,"docs":"","sig":null,"attributes":[]},{"kind":"Local","id":{"krate":0,"index":3154116648},"span":{"file_name":"src\\main.rs","byte_start":5611,"byte_end":5614,"line_start":207,"line_end":207,"column_start":9,"column_end":12},"name":"dir","qualname":"dir$HirId { owner: DefId(0:40 ~ othello[8f26]::place_piece), local_id: 61 }","value":"&[i32; 2]","parent":null,"children":[],"decl_id":null,"docs":"","sig":null,"attributes":[]},{"kind":"Local","id":{"krate":0,"index":3791650856},"span":{"file_name":"src\\main.rs","byte_start":5648,"byte_end":5652,"line_start":208,"line_end":208,"column_start":17,"column_end":21},"name":"dist","qualname":"dist$HirId { owner: DefId(0:40 ~ othello[8f26]::place_piece), local_id: 71 }","value":"i32","parent":null,"children":[],"decl_id":null,"docs":"","sig":null,"attributes":[]},{"kind":"Local","id":{"krate":0,"index":3523215400},"span":{"file_name":"src\\main.rs","byte_start":5674,"byte_end":5679,"line_start":209,"line_end":209,"column_start":17,"column_end":22},"name":"found","qualname":"found$HirId { owner: DefId(0:40 ~ othello[8f26]::place_piece), local_id: 75 }","value":"bool","parent":null,"children":[],"decl_id":null,"docs":"","sig":null,"attributes":[]},{"kind":"Local","id":{"krate":0,"index":3120562216},"span":{"file_name":"src\\main.rs","byte_start":5720,"byte_end":5721,"line_start":211,"line_end":211,"column_start":17,"column_end":18},"name":"x","qualname":"x$HirId { owner: DefId(0:40 ~ othello[8f26]::place_piece), local_id: 93 }","value":"i32","parent":null,"children":[],"decl_id":null,"docs":"","sig":null,"attributes":[]},{"kind":"Local","id":{"krate":0,"index":4127195176},"span":{"file_name":"src\\main.rs","byte_start":5771,"byte_end":5772,"line_start":212,"line_end":212,"column_start":17,"column_end":18},"name":"y","qualname":"y$HirId { owner: DefId(0:40 ~ othello[8f26]::place_piece), local_id: 111 }","value":"i32","parent":null,"children":[],"decl_id":null,"docs":"","sig":null,"attributes":[]},{"kind":"Local","id":{"krate":0,"index":1258291240},"span":{"file_name":"src\\main.rs","byte_start":6217,"byte_end":6218,"line_start":225,"line_end":225,"column_start":17,"column_end":18},"name":"i","qualname":"i$HirId { owner: DefId(0:40 ~ othello[8f26]::place_piece), local_id: 210 }","value":"i32","parent":null,"children":[],"decl_id":null,"docs":"","sig":null,"attributes":[]},{"kind":"Local","id":{"krate":0,"index":1459617832},"span":{"file_name":"src\\main.rs","byte_start":6252,"byte_end":6253,"line_start":226,"line_end":226,"column_start":21,"column_end":22},"name":"x","qualname":"x$HirId { owner: DefId(0:40 ~ othello[8f26]::place_piece), local_id: 234 }","value":"i32","parent":null,"children":[],"decl_id":null,"docs":"","sig":null,"attributes":[]},{"kind":"Local","id":{"krate":0,"index":1056964648},"span":{"file_name":"src\\main.rs","byte_start":6304,"byte_end":6305,"line_start":227,"line_end":227,"column_start":21,"column_end":22},"name":"y","qualname":"y$HirId { owner: DefId(0:40 ~ othello[8f26]::place_piece), local_id: 252 }","value":"i32","parent":null,"children":[],"decl_id":null,"docs":"","sig":null,"attributes":[]},{"kind":"Function","id":{"krate":0,"index":44},"span":{"file_name":"src\\main.rs","byte_start":6434,"byte_end":6438,"line_start":234,"line_end":234,"column_start":4,"column_end":8},"name":"main","qualname":"::main","value":"fn main()","parent":null,"children":[],"decl_id":null,"docs":"","sig":null,"attributes":[]},{"kind":"Local","id":{"krate":0,"index":1610612780},"span":{"file_name":"src\\main.rs","byte_start":6455,"byte_end":6460,"line_start":235,"line_end":235,"column_start":13,"column_end":18},"name":"board","qualname":"board$HirId { owner: DefId(0:44 ~ othello[8f26]::main), local_id: 6 }","value":"[[Spot; 8]; 8]","parent":null,"children":[],"decl_id":null,"docs":"","sig":null,"attributes":[]},{"kind":"Local","id":{"krate":0,"index":805306412},"span":{"file_name":"src\\main.rs","byte_start":6525,"byte_end":6537,"line_start":237,"line_end":237,"column_start":13,"column_end":25},"name":"current_turn","qualname":"current_turn$HirId { owner: DefId(0:44 ~ othello[8f26]::main), local_id: 12 }","value":"Spot","parent":null,"children":[],"decl_id":null,"docs":"","sig":null,"attributes":[]},{"kind":"Local","id":{"krate":0,"index":1744830508},"span":{"file_name":"src\\main.rs","byte_start":6616,"byte_end":6627,"line_start":241,"line_end":241,"column_start":13,"column_end":24},"name":"valid_moves","qualname":"valid_moves$HirId { owner: DefId(0:44 ~ othello[8f26]::main), local_id: 22 }","value":"[[bool; 8]; 8]","parent":null,"children":[],"decl_id":null,"docs":"","sig":null,"attributes":[]},{"kind":"Local","id":{"krate":0,"index":335544364},"span":{"file_name":"src\\main.rs","byte_start":6735,"byte_end":6740,"line_start":243,"line_end":243,"column_start":13,"column_end":18},"name":"input","qualname":"input$HirId { owner: DefId(0:44 ~ othello[8f26]::main), local_id: 40 }","value":"[usize; 2]","parent":null,"children":[],"decl_id":null,"docs":"","sig":null,"attributes":[]}],"impls":[{"id":0,"kind":"Inherent","span":{"file_name":"src\\main.rs","byte_start":112,"byte_end":116,"line_start":9,"line_end":9,"column_start":6,"column_end":10},"value":"","parent":null,"children":[{"krate":0,"index":5},{"krate":0,"index":6}],"docs":"","sig":null,"attributes":[]}],"refs":[{"kind":"Mod","span":{"file_name":"src\\main.rs","byte_start":4,"byte_end":7,"line_start":1,"line_end":1,"column_start":5,"column_end":8},"ref_id":{"krate":1,"index":0}},{"kind":"Mod","span":{"file_name":"src\\main.rs","byte_start":9,"byte_end":11,"line_start":1,"line_end":1,"column_start":10,"column_end":12},"ref_id":{"krate":1,"index":3371}},{"kind":"Mod","span":{"file_name":"src\\main.rs","byte_start":13,"byte_end":20,"line_start":1,"line_end":1,"column_start":14,"column_end":21},"ref_id":{"krate":1,"index":4222}},{"kind":"Type","span":{"file_name":"src\\main.rs","byte_start":112,"byte_end":116,"line_start":9,"line_end":9,"column_start":6,"column_end":10},"ref_id":{"krate":0,"index":45}},{"kind":"Variable","span":{"file_name":"src\\main.rs","byte_start":174,"byte_end":178,"line_start":11,"line_end":11,"column_start":15,"column_end":19},"ref_id":{"krate":0,"index":1073741829}},{"kind":"Type","span":{"file_name":"src\\main.rs","byte_start":199,"byte_end":204,"line_start":12,"line_end":12,"column_start":19,"column_end":24},"ref_id":{"krate":0,"index":48}},{"kind":"Type","span":{"file_name":"src\\main.rs","byte_start":193,"byte_end":197,"line_start":12,"line_end":12,"column_start":13,"column_end":17},"ref_id":{"krate":0,"index":45}},{"kind":"Type","span":{"file_name":"src\\main.rs","byte_start":199,"byte_end":204,"line_start":12,"line_end":12,"column_start":19,"column_end":24},"ref_id":{"krate":0,"index":48}},{"kind":"Type","span":{"file_name":"src\\main.rs","byte_start":193,"byte_end":197,"line_start":12,"line_end":12,"column_start":13,"column_end":17},"ref_id":{"krate":0,"index":45}},{"kind":"Type","span":{"file_name":"src\\main.rs","byte_start":231,"byte_end":236,"line_start":13,"line_end":13,"column_start":19,"column_end":24},"ref_id":{"krate":0,"index":50}},{"kind":"Type","span":{"file_name":"src\\main.rs","byte_start":225,"byte_end":229,"line_start":13,"line_end":13,"column_start":13,"column_end":17},"ref_id":{"krate":0,"index":45}},{"kind":"Type","span":{"file_name":"src\\main.rs","byte_start":231,"byte_end":236,"line_start":13,"line_end":13,"column_start":19,"column_end":24},"ref_id":{"krate":0,"index":50}},{"kind":"Type","span":{"file_name":"src\\main.rs","byte_start":225,"byte_end":229,"line_start":13,"line_end":13,"column_start":13,"column_end":17},"ref_id":{"krate":0,"index":45}},{"kind":"Type","span":{"file_name":"src\\main.rs","byte_start":263,"byte_end":268,"line_start":14,"line_end":14,"column_start":19,"column_end":24},"ref_id":{"krate":0,"index":46}},{"kind":"Type","span":{"file_name":"src\\main.rs","byte_start":257,"byte_end":261,"line_start":14,"line_end":14,"column_start":13,"column_end":17},"ref_id":{"krate":0,"index":45}},{"kind":"Type","span":{"file_name":"src\\main.rs","byte_start":263,"byte_end":268,"line_start":14,"line_end":14,"column_start":19,"column_end":24},"ref_id":{"krate":0,"index":46}},{"kind":"Type","span":{"file_name":"src\\main.rs","byte_start":257,"byte_end":261,"line_start":14,"line_end":14,"column_start":13,"column_end":17},"ref_id":{"krate":0,"index":45}},{"kind":"Type","span":{"file_name":"src\\main.rs","byte_start":318,"byte_end":322,"line_start":17,"line_end":17,"column_start":26,"column_end":30},"ref_id":{"krate":0,"index":45}},{"kind":"Variable","span":{"file_name":"src\\main.rs","byte_start":339,"byte_end":343,"line_start":18,"line_end":18,"column_start":15,"column_end":19},"ref_id":{"krate":0,"index":1073741830}},{"kind":"Type","span":{"file_name":"src\\main.rs","byte_start":364,"byte_end":369,"line_start":19,"line_end":19,"column_start":19,"column_end":24},"ref_id":{"krate":0,"index":48}},{"kind":"Type","span":{"file_name":"src\\main.rs","byte_start":358,"byte_end":362,"line_start":19,"line_end":19,"column_start":13,"column_end":17},"ref_id":{"krate":0,"index":45}},{"kind":"Type","span":{"file_name":"src\\main.rs","byte_start":364,"byte_end":369,"line_start":19,"line_end":19,"column_start":19,"column_end":24},"ref_id":{"krate":0,"index":48}},{"kind":"Type","span":{"file_name":"src\\main.rs","byte_start":358,"byte_end":362,"line_start":19,"line_end":19,"column_start":13,"column_end":17},"ref_id":{"krate":0,"index":45}},{"kind":"Type","span":{"file_name":"src\\main.rs","byte_start":379,"byte_end":384,"line_start":19,"line_end":19,"column_start":34,"column_end":39},"ref_id":{"krate":0,"index":50}},{"kind":"Type","span":{"file_name":"src\\main.rs","byte_start":373,"byte_end":377,"line_start":19,"line_end":19,"column_start":28,"column_end":32},"ref_id":{"krate":0,"index":45}},{"kind":"Type","span":{"file_name":"src\\main.rs","byte_start":404,"byte_end":409,"line_start":20,"line_end":20,"column_start":19,"column_end":24},"ref_id":{"krate":0,"index":50}},{"kind":"Type","span":{"file_name":"src\\main.rs","byte_start":398,"byte_end":402,"line_start":20,"line_end":20,"column_start":13,"column_end":17},"ref_id":{"krate":0,"index":45}},{"kind":"Type","span":{"file_name":"src\\main.rs","byte_start":404,"byte_end":409,"line_start":20,"line_end":20,"column_start":19,"column_end":24},"ref_id":{"krate":0,"index":50}},{"kind":"Type","span":{"file_name":"src\\main.rs","byte_start":398,"byte_end":402,"line_start":20,"line_end":20,"column_start":13,"column_end":17},"ref_id":{"krate":0,"index":45}},{"kind":"Type","span":{"file_name":"src\\main.rs","byte_start":419,"byte_end":424,"line_start":20,"line_end":20,"column_start":34,"column_end":39},"ref_id":{"krate":0,"index":48}},{"kind":"Type","span":{"file_name":"src\\main.rs","byte_start":413,"byte_end":417,"line_start":20,"line_end":20,"column_start":28,"column_end":32},"ref_id":{"krate":0,"index":45}},{"kind":"Type","span":{"file_name":"src\\main.rs","byte_start":444,"byte_end":449,"line_start":21,"line_end":21,"column_start":19,"column_end":24},"ref_id":{"krate":0,"index":46}},{"kind":"Type","span":{"file_name":"src\\main.rs","byte_start":438,"byte_end":442,"line_start":21,"line_end":21,"column_start":13,"column_end":17},"ref_id":{"krate":0,"index":45}},{"kind":"Type","span":{"file_name":"src\\main.rs","byte_start":444,"byte_end":449,"line_start":21,"line_end":21,"column_start":19,"column_end":24},"ref_id":{"krate":0,"index":46}},{"kind":"Type","span":{"file_name":"src\\main.rs","byte_start":438,"byte_end":442,"line_start":21,"line_end":21,"column_start":13,"column_end":17},"ref_id":{"krate":0,"index":45}},{"kind":"Type","span":{"file_name":"src\\main.rs","byte_start":459,"byte_end":464,"line_start":21,"line_end":21,"column_start":34,"column_end":39},"ref_id":{"krate":0,"index":46}},{"kind":"Type","span":{"file_name":"src\\main.rs","byte_start":453,"byte_end":457,"line_start":21,"line_end":21,"column_start":28,"column_end":32},"ref_id":{"krate":0,"index":45}},{"kind":"Type","span":{"file_name":"src\\main.rs","byte_start":563,"byte_end":567,"line_start":30,"line_end":30,"column_start":24,"column_end":28},"ref_id":{"krate":0,"index":45}},{"kind":"Type","span":{"file_name":"src\\main.rs","byte_start":606,"byte_end":611,"line_start":31,"line_end":31,"column_start":29,"column_end":34},"ref_id":{"krate":0,"index":46}},{"kind":"Type","span":{"file_name":"src\\main.rs","byte_start":600,"byte_end":604,"line_start":31,"line_end":31,"column_start":23,"column_end":27},"ref_id":{"krate":0,"index":45}},{"kind":"Type","span":{"file_name":"src\\main.rs","byte_start":645,"byte_end":650,"line_start":32,"line_end":32,"column_start":25,"column_end":30},"ref_id":{"krate":0,"index":50}},{"kind":"Type","span":{"file_name":"src\\main.rs","byte_start":639,"byte_end":643,"line_start":32,"line_end":32,"column_start":19,"column_end":23},"ref_id":{"krate":0,"index":45}},{"kind":"Variable","span":{"file_name":"src\\main.rs","byte_start":625,"byte_end":630,"line_start":32,"line_end":32,"column_start":5,"column_end":10},"ref_id":{"krate":0,"index":805306376}},{"kind":"Type","span":{"file_name":"src\\main.rs","byte_start":676,"byte_end":681,"line_start":33,"line_end":33,"column_start":25,"column_end":30},"ref_id":{"krate":0,"index":48}},{"kind":"Type","span":{"file_name":"src\\main.rs","byte_start":670,"byte_end":674,"line_start":33,"line_end":33,"column_start":19,"column_end":23},"ref_id":{"krate":0,"index":45}},{"kind":"Variable","span":{"file_name":"src\\main.rs","byte_start":656,"byte_end":661,"line_start":33,"line_end":33,"column_start":5,"column_end":10},"ref_id":{"krate":0,"index":805306376}},{"kind":"Type","span":{"file_name":"src\\main.rs","byte_start":707,"byte_end":712,"line_start":34,"line_end":34,"column_start":25,"column_end":30},"ref_id":{"krate":0,"index":48}},{"kind":"Type","span":{"file_name":"src\\main.rs","byte_start":701,"byte_end":705,"line_start":34,"line_end":34,"column_start":19,"column_end":23},"ref_id":{"krate":0,"index":45}},{"kind":"Variable","span":{"file_name":"src\\main.rs","byte_start":687,"byte_end":692,"line_start":34,"line_end":34,"column_start":5,"column_end":10},"ref_id":{"krate":0,"index":805306376}},{"kind":"Type","span":{"file_name":"src\\main.rs","byte_start":738,"byte_end":743,"line_start":35,"line_end":35,"column_start":25,"column_end":30},"ref_id":{"krate":0,"index":50}},{"kind":"Type","span":{"file_name":"src\\main.rs","byte_start":732,"byte_end":736,"line_start":35,"line_end":35,"column_start":19,"column_end":23},"ref_id":{"krate":0,"index":45}},{"kind":"Variable","span":{"file_name":"src\\main.rs","byte_start":718,"byte_end":723,"line_start":35,"line_end":35,"column_start":5,"column_end":10},"ref_id":{"krate":0,"index":805306376}},{"kind":"Variable","span":{"file_name":"src\\main.rs","byte_start":749,"byte_end":754,"line_start":36,"line_end":36,"column_start":5,"column_end":10},"ref_id":{"krate":0,"index":805306376}},{"kind":"Type","span":{"file_name":"src\\main.rs","byte_start":781,"byte_end":785,"line_start":39,"line_end":39,"column_start":24,"column_end":28},"ref_id":{"krate":0,"index":45}},{"kind":"Type","span":{"file_name":"src\\main.rs","byte_start":838,"byte_end":842,"line_start":39,"line_end":39,"column_start":81,"column_end":85},"ref_id":{"krate":0,"index":45}},{"kind":"Function","span":{"file_name":"src\\main.rs","byte_start":850,"byte_end":862,"line_start":40,"line_end":40,"column_start":5,"column_end":17},"ref_id":{"krate":0,"index":7}},{"kind":"Type","span":{"file_name":"src\\main.rs","byte_start":897,"byte_end":900,"line_start":42,"line_end":42,"column_start":31,"column_end":34},"ref_id":{"krate":5,"index":7089}},{"kind":"Type","span":{"file_name":"src\\main.rs","byte_start":1019,"byte_end":1023,"line_start":46,"line_end":46,"column_start":14,"column_end":18},"ref_id":{"krate":2,"index":44482}},{"kind":"Variable","span":{"file_name":"src\\main.rs","byte_start":1019,"byte_end":1020,"line_start":46,"line_end":46,"column_start":14,"column_end":15},"ref_id":{"krate":2,"index":44484}},{"kind":"Variable","span":{"file_name":"src\\main.rs","byte_start":1022,"byte_end":1023,"line_start":46,"line_end":46,"column_start":17,"column_end":18},"ref_id":{"krate":2,"index":44485}},{"kind":"Variable","span":{"file_name":"src\\main.rs","byte_start":1051,"byte_end":1052,"line_start":47,"line_end":47,"column_start":26,"column_end":27},"ref_id":{"krate":0,"index":2986344461}},{"kind":"Type","span":{"file_name":"src\\main.rs","byte_start":1076,"byte_end":1080,"line_start":48,"line_end":48,"column_start":18,"column_end":22},"ref_id":{"krate":2,"index":44482}},{"kind":"Variable","span":{"file_name":"src\\main.rs","byte_start":1076,"byte_end":1077,"line_start":48,"line_end":48,"column_start":18,"column_end":19},"ref_id":{"krate":2,"index":44484}},{"kind":"Variable","span":{"file_name":"src\\main.rs","byte_start":1079,"byte_end":1080,"line_start":48,"line_end":48,"column_start":21,"column_end":22},"ref_id":{"krate":2,"index":44485}},{"kind":"Variable","span":{"file_name":"src\\main.rs","byte_start":1098,"byte_end":1109,"line_start":49,"line_end":49,"column_start":16,"column_end":27},"ref_id":{"krate":0,"index":536870925}},{"kind":"Variable","span":{"file_name":"src\\main.rs","byte_start":1110,"byte_end":1111,"line_start":49,"line_end":49,"column_start":28,"column_end":29},"ref_id":{"krate":0,"index":1577058317}},{"kind":"Variable","span":{"file_name":"src\\main.rs","byte_start":1113,"byte_end":1114,"line_start":49,"line_end":49,"column_start":31,"column_end":32},"ref_id":{"krate":0,"index":2986344461}},{"kind":"Function","span":{"file_name":"src\\main.rs","byte_start":1181,"byte_end":1185,"line_start":51,"line_end":51,"column_start":34,"column_end":38},"ref_id":{"krate":5,"index":7170}},{"kind":"Variable","span":{"file_name":"src\\main.rs","byte_start":1164,"byte_end":1180,"line_start":51,"line_end":51,"column_start":17,"column_end":33},"ref_id":{"krate":0,"index":3623878669}},{"kind":"Variable","span":{"file_name":"src\\main.rs","byte_start":1187,"byte_end":1188,"line_start":51,"line_end":51,"column_start":40,"column_end":41},"ref_id":{"krate":0,"index":2986344461}},{"kind":"Variable","span":{"file_name":"src\\main.rs","byte_start":1190,"byte_end":1191,"line_start":51,"line_end":51,"column_start":43,"column_end":44},"ref_id":{"krate":0,"index":1577058317}},{"kind":"Function","span":{"file_name":"src\\main.rs","byte_start":1413,"byte_end":1422,"line_start":57,"line_end":57,"column_start":43,"column_end":52},"ref_id":{"krate":0,"index":5}},{"kind":"Variable","span":{"file_name":"src\\main.rs","byte_start":1401,"byte_end":1406,"line_start":57,"line_end":57,"column_start":31,"column_end":36},"ref_id":{"krate":0,"index":1073741837}},{"kind":"Variable","span":{"file_name":"src\\main.rs","byte_start":1407,"byte_end":1408,"line_start":57,"line_end":57,"column_start":37,"column_end":38},"ref_id":{"krate":0,"index":1577058317}},{"kind":"Variable","span":{"file_name":"src\\main.rs","byte_start":1410,"byte_end":1411,"line_start":57,"line_end":57,"column_start":40,"column_end":41},"ref_id":{"krate":0,"index":2986344461}},{"kind":"Function","span":{"file_name":"src\\main.rs","byte_start":1600,"byte_end":1604,"line_start":66,"line_end":66,"column_start":22,"column_end":26},"ref_id":{"krate":2,"index":11513}},{"kind":"Variable","span":{"file_name":"src\\main.rs","byte_start":1594,"byte_end":1599,"line_start":66,"line_end":66,"column_start":16,"column_end":21},"ref_id":{"krate":0,"index":1073741837}},{"kind":"Function","span":{"file_name":"src\\main.rs","byte_start":1633,"byte_end":1637,"line_start":67,"line_end":67,"column_start":25,"column_end":29},"ref_id":{"krate":2,"index":11513}},{"kind":"Variable","span":{"file_name":"src\\main.rs","byte_start":1629,"byte_end":1632,"line_start":67,"line_end":67,"column_start":21,"column_end":24},"ref_id":{"krate":0,"index":3028287501}},{"kind":"Variable","span":{"file_name":"src\\main.rs","byte_start":1660,"byte_end":1664,"line_start":68,"line_end":68,"column_start":19,"column_end":23},"ref_id":{"krate":0,"index":478150669}},{"kind":"Type","span":{"file_name":"src\\main.rs","byte_start":1689,"byte_end":1694,"line_start":69,"line_end":69,"column_start":23,"column_end":28},"ref_id":{"krate":0,"index":48}},{"kind":"Type","span":{"file_name":"src\\main.rs","byte_start":1683,"byte_end":1687,"line_start":69,"line_end":69,"column_start":17,"column_end":21},"ref_id":{"krate":0,"index":45}},{"kind":"Type","span":{"file_name":"src\\main.rs","byte_start":1689,"byte_end":1694,"line_start":69,"line_end":69,"column_start":23,"column_end":28},"ref_id":{"krate":0,"index":48}},{"kind":"Type","span":{"file_name":"src\\main.rs","byte_start":1683,"byte_end":1687,"line_start":69,"line_end":69,"column_start":17,"column_end":21},"ref_id":{"krate":0,"index":45}},{"kind":"Variable","span":{"file_name":"src\\main.rs","byte_start":1698,"byte_end":1709,"line_start":69,"line_end":69,"column_start":32,"column_end":43},"ref_id":{"krate":0,"index":612368397}},{"kind":"Type","span":{"file_name":"src\\main.rs","byte_start":1738,"byte_end":1743,"line_start":70,"line_end":70,"column_start":23,"column_end":28},"ref_id":{"krate":0,"index":50}},{"kind":"Type","span":{"file_name":"src\\main.rs","byte_start":1732,"byte_end":1736,"line_start":70,"line_end":70,"column_start":17,"column_end":21},"ref_id":{"krate":0,"index":45}},{"kind":"Type","span":{"file_name":"src\\main.rs","byte_start":1738,"byte_end":1743,"line_start":70,"line_end":70,"column_start":23,"column_end":28},"ref_id":{"krate":0,"index":50}},{"kind":"Type","span":{"file_name":"src\\main.rs","byte_start":1732,"byte_end":1736,"line_start":70,"line_end":70,"column_start":17,"column_end":21},"ref_id":{"krate":0,"index":45}},{"kind":"Variable","span":{"file_name":"src\\main.rs","byte_start":1747,"byte_end":1758,"line_start":70,"line_end":70,"column_start":32,"column_end":43},"ref_id":{"krate":0,"index":343932941}},{"kind":"Variable","span":{"file_name":"src\\main.rs","byte_start":1845,"byte_end":1856,"line_start":75,"line_end":75,"column_start":26,"column_end":37},"ref_id":{"krate":0,"index":612368397}},{"kind":"Variable","span":{"file_name":"src\\main.rs","byte_start":1883,"byte_end":1894,"line_start":76,"line_end":76,"column_start":25,"column_end":36},"ref_id":{"krate":0,"index":343932941}},{"kind":"Variable","span":{"file_name":"src\\main.rs","byte_start":1905,"byte_end":1917,"line_start":78,"line_end":78,"column_start":8,"column_end":20},"ref_id":{"krate":0,"index":1610612749}},{"kind":"Type","span":{"file_name":"src\\main.rs","byte_start":1927,"byte_end":1932,"line_start":78,"line_end":78,"column_start":30,"column_end":35},"ref_id":{"krate":0,"index":46}},{"kind":"Type","span":{"file_name":"src\\main.rs","byte_start":1921,"byte_end":1925,"line_start":78,"line_end":78,"column_start":24,"column_end":28},"ref_id":{"krate":0,"index":45}},{"kind":"Function","span":{"file_name":"src\\main.rs","byte_start":1985,"byte_end":1994,"line_start":79,"line_end":79,"column_start":51,"column_end":60},"ref_id":{"krate":0,"index":5}},{"kind":"Variable","span":{"file_name":"src\\main.rs","byte_start":1972,"byte_end":1984,"line_start":79,"line_end":79,"column_start":38,"column_end":50},"ref_id":{"krate":0,"index":1610612749}},{"kind":"Function","span":{"file_name":"src\\main.rs","byte_start":2231,"byte_end":2240,"line_start":84,"line_end":84,"column_start":49,"column_end":58},"ref_id":{"krate":2,"index":7948}},{"kind":"Function","span":{"file_name":"src\\main.rs","byte_start":2224,"byte_end":2228,"line_start":84,"line_end":84,"column_start":42,"column_end":46},"ref_id":{"krate":2,"index":11513}},{"kind":"Variable","span":{"file_name":"src\\main.rs","byte_start":2207,"byte_end":2223,"line_start":84,"line_end":84,"column_start":25,"column_end":41},"ref_id":{"krate":0,"index":3623878669}},{"kind":"Variable","span":{"file_name":"src\\main.rs","byte_start":2275,"byte_end":2278,"line_start":85,"line_end":85,"column_start":31,"column_end":34},"ref_id":{"krate":0,"index":4286578701}},{"kind":"Variable","span":{"file_name":"src\\main.rs","byte_start":2287,"byte_end":2290,"line_start":85,"line_end":85,"column_start":43,"column_end":46},"ref_id":{"krate":0,"index":4286578701}},{"kind":"Variable","span":{"file_name":"src\\main.rs","byte_start":2315,"byte_end":2316,"line_start":86,"line_end":86,"column_start":16,"column_end":17},"ref_id":{"krate":0,"index":2139095053}},{"kind":"Function","span":{"file_name":"src\\main.rs","byte_start":2337,"byte_end":2340,"line_start":86,"line_end":86,"column_start":38,"column_end":41},"ref_id":{"krate":5,"index":7177}},{"kind":"Variable","span":{"file_name":"src\\main.rs","byte_start":2320,"byte_end":2336,"line_start":86,"line_end":86,"column_start":21,"column_end":37},"ref_id":{"krate":0,"index":3623878669}},{"kind":"Variable","span":{"file_name":"src\\main.rs","byte_start":2611,"byte_end":2618,"line_start":98,"line_end":98,"column_start":20,"column_end":27},"ref_id":{"krate":0,"index":536870931}},{"kind":"Function","span":{"file_name":"src\\main.rs","byte_start":2625,"byte_end":2634,"line_start":99,"line_end":99,"column_start":5,"column_end":14},"ref_id":{"krate":0,"index":23}},{"kind":"Variable","span":{"file_name":"src\\main.rs","byte_start":2635,"byte_end":2646,"line_start":99,"line_end":99,"column_start":15,"column_end":26},"ref_id":{"krate":0,"index":1073741843}},{"kind":"Function","span":{"file_name":"src\\main.rs","byte_start":2785,"byte_end":2791,"line_start":105,"line_end":105,"column_start":31,"column_end":37},"ref_id":{"krate":2,"index":8970}},{"kind":"Function","span":{"file_name":"src\\main.rs","byte_start":2777,"byte_end":2782,"line_start":105,"line_end":105,"column_start":23,"column_end":28},"ref_id":{"krate":1,"index":4690}},{"kind":"Function","span":{"file_name":"src\\main.rs","byte_start":2768,"byte_end":2774,"line_start":105,"line_end":105,"column_start":14,"column_end":20},"ref_id":{"krate":1,"index":4431}},{"kind":"Mod","span":{"file_name":"src\\main.rs","byte_start":2759,"byte_end":2762,"line_start":105,"line_end":105,"column_start":5,"column_end":8},"ref_id":{"krate":1,"index":0}},{"kind":"Mod","span":{"file_name":"src\\main.rs","byte_start":2764,"byte_end":2766,"line_start":105,"line_end":105,"column_start":10,"column_end":12},"ref_id":{"krate":1,"index":3371}},{"kind":"Function","span":{"file_name":"src\\main.rs","byte_start":2823,"byte_end":2826,"line_start":106,"line_end":106,"column_start":29,"column_end":32},"ref_id":{"krate":5,"index":5548}},{"kind":"Type","span":{"file_name":"src\\main.rs","byte_start":2815,"byte_end":2821,"line_start":106,"line_end":106,"column_start":21,"column_end":27},"ref_id":{"krate":5,"index":7626}},{"kind":"Function","span":{"file_name":"src\\main.rs","byte_start":2891,"byte_end":2897,"line_start":109,"line_end":109,"column_start":10,"column_end":16},"ref_id":{"krate":2,"index":8969}},{"kind":"Function","span":{"file_name":"src\\main.rs","byte_start":2860,"byte_end":2869,"line_start":108,"line_end":108,"column_start":10,"column_end":19},"ref_id":{"krate":1,"index":4396}},{"kind":"Function","span":{"file_name":"src\\main.rs","byte_start":2843,"byte_end":2848,"line_start":107,"line_end":107,"column_start":14,"column_end":19},"ref_id":{"krate":1,"index":4390}},{"kind":"Mod","span":{"file_name":"src\\main.rs","byte_start":2834,"byte_end":2837,"line_start":107,"line_end":107,"column_start":5,"column_end":8},"ref_id":{"krate":1,"index":0}},{"kind":"Mod","span":{"file_name":"src\\main.rs","byte_start":2839,"byte_end":2841,"line_start":107,"line_end":107,"column_start":10,"column_end":12},"ref_id":{"krate":1,"index":3371}},{"kind":"Variable","span":{"file_name":"src\\main.rs","byte_start":2875,"byte_end":2880,"line_start":108,"line_end":108,"column_start":25,"column_end":30},"ref_id":{"krate":0,"index":3825205271}},{"kind":"Function","span":{"file_name":"src\\main.rs","byte_start":2958,"byte_end":2963,"line_start":110,"line_end":110,"column_start":37,"column_end":42},"ref_id":{"krate":2,"index":12667}},{"kind":"Function","span":{"file_name":"src\\main.rs","byte_start":2951,"byte_end":2955,"line_start":110,"line_end":110,"column_start":30,"column_end":34},"ref_id":{"krate":2,"index":12706}},{"kind":"Variable","span":{"file_name":"src\\main.rs","byte_start":2945,"byte_end":2950,"line_start":110,"line_end":110,"column_start":24,"column_end":29},"ref_id":{"krate":0,"index":3825205271}},{"kind":"Variable","span":{"file_name":"src\\main.rs","byte_start":3045,"byte_end":3057,"line_start":114,"line_end":114,"column_start":14,"column_end":26},"ref_id":{"krate":0,"index":4227858455}},{"kind":"Variable","span":{"file_name":"src\\main.rs","byte_start":3071,"byte_end":3076,"line_start":115,"line_end":115,"column_start":12,"column_end":17},"ref_id":{"krate":0,"index":3254779927}},{"kind":"Function","span":{"file_name":"src\\main.rs","byte_start":3103,"byte_end":3115,"line_start":116,"line_end":116,"column_start":20,"column_end":32},"ref_id":{"krate":0,"index":19}},{"kind":"Variable","span":{"file_name":"src\\main.rs","byte_start":3133,"byte_end":3144,"line_start":117,"line_end":117,"column_start":17,"column_end":28},"ref_id":{"krate":0,"index":1073741847}},{"kind":"Function","span":{"file_name":"src\\main.rs","byte_start":3259,"byte_end":3262,"line_start":120,"line_end":120,"column_start":21,"column_end":24},"ref_id":{"krate":2,"index":12618}},{"kind":"Variable","span":{"file_name":"src\\main.rs","byte_start":3257,"byte_end":3258,"line_start":120,"line_end":120,"column_start":19,"column_end":20},"ref_id":{"krate":0,"index":1241514007}},{"kind":"Function","span":{"file_name":"src\\main.rs","byte_start":3291,"byte_end":3303,"line_start":121,"line_end":121,"column_start":20,"column_end":32},"ref_id":{"krate":0,"index":19}},{"kind":"Variable","span":{"file_name":"src\\main.rs","byte_start":3304,"byte_end":3315,"line_start":121,"line_end":121,"column_start":33,"column_end":44},"ref_id":{"krate":0,"index":1073741847}},{"kind":"Function","span":{"file_name":"src\\main.rs","byte_start":3386,"byte_end":3391,"line_start":123,"line_end":123,"column_start":21,"column_end":26},"ref_id":{"krate":2,"index":12735}},{"kind":"Variable","span":{"file_name":"src\\main.rs","byte_start":3384,"byte_end":3385,"line_start":123,"line_end":123,"column_start":19,"column_end":20},"ref_id":{"krate":0,"index":1241514007}},{"kind":"Variable","span":{"file_name":"src\\main.rs","byte_start":3418,"byte_end":3421,"line_start":124,"line_end":124,"column_start":15,"column_end":18},"ref_id":{"krate":0,"index":553648151}},{"kind":"Type","span":{"file_name":"src\\main.rs","byte_start":3436,"byte_end":3438,"line_start":125,"line_end":125,"column_start":13,"column_end":15},"ref_id":{"krate":2,"index":46101}},{"kind":"Type","span":{"file_name":"src\\main.rs","byte_start":3436,"byte_end":3438,"line_start":125,"line_end":125,"column_start":13,"column_end":15},"ref_id":{"krate":2,"index":46101}},{"kind":"Variable","span":{"file_name":"src\\main.rs","byte_start":3466,"byte_end":3467,"line_start":126,"line_end":126,"column_start":20,"column_end":21},"ref_id":{"krate":0,"index":285212695}},{"kind":"Function","span":{"file_name":"src\\main.rs","byte_start":3501,"byte_end":3513,"line_start":127,"line_end":127,"column_start":28,"column_end":40},"ref_id":{"krate":0,"index":19}},{"kind":"Variable","span":{"file_name":"src\\main.rs","byte_start":3514,"byte_end":3525,"line_start":127,"line_end":127,"column_start":41,"column_end":52},"ref_id":{"krate":0,"index":1073741847}},{"kind":"Variable","span":{"file_name":"src\\main.rs","byte_start":3613,"byte_end":3614,"line_start":129,"line_end":129,"column_start":30,"column_end":31},"ref_id":{"krate":0,"index":285212695}},{"kind":"Variable","span":{"file_name":"src\\main.rs","byte_start":3600,"byte_end":3603,"line_start":129,"line_end":129,"column_start":17,"column_end":20},"ref_id":{"krate":0,"index":4060086295}},{"kind":"Variable","span":{"file_name":"src\\main.rs","byte_start":3604,"byte_end":3609,"line_start":129,"line_end":129,"column_start":21,"column_end":26},"ref_id":{"krate":0,"index":3254779927}},{"kind":"Type","span":{"file_name":"src\\main.rs","byte_start":3646,"byte_end":3649,"line_start":131,"line_end":131,"column_start":13,"column_end":16},"ref_id":{"krate":2,"index":46104}},{"kind":"Type","span":{"file_name":"src\\main.rs","byte_start":3646,"byte_end":3649,"line_start":131,"line_end":131,"column_start":13,"column_end":16},"ref_id":{"krate":2,"index":46104}},{"kind":"Function","span":{"file_name":"src\\main.rs","byte_start":3663,"byte_end":3675,"line_start":131,"line_end":131,"column_start":30,"column_end":42},"ref_id":{"krate":0,"index":19}},{"kind":"Variable","span":{"file_name":"src\\main.rs","byte_start":3676,"byte_end":3687,"line_start":131,"line_end":131,"column_start":43,"column_end":54},"ref_id":{"krate":0,"index":1073741847}},{"kind":"Variable","span":{"file_name":"src\\main.rs","byte_start":3746,"byte_end":3751,"line_start":133,"line_end":133,"column_start":9,"column_end":14},"ref_id":{"krate":0,"index":3254779927}},{"kind":"Variable","span":{"file_name":"src\\main.rs","byte_start":3771,"byte_end":3776,"line_start":135,"line_end":135,"column_start":8,"column_end":13},"ref_id":{"krate":0,"index":3254779927}},{"kind":"Function","span":{"file_name":"src\\main.rs","byte_start":3792,"byte_end":3804,"line_start":136,"line_end":136,"column_start":9,"column_end":21},"ref_id":{"krate":0,"index":19}},{"kind":"Variable","span":{"file_name":"src\\main.rs","byte_start":3818,"byte_end":3829,"line_start":137,"line_end":137,"column_start":13,"column_end":24},"ref_id":{"krate":0,"index":1073741847}},{"kind":"Variable","span":{"file_name":"src\\main.rs","byte_start":3930,"byte_end":3941,"line_start":140,"line_end":140,"column_start":16,"column_end":27},"ref_id":{"krate":0,"index":1073741847}},{"kind":"Variable","span":{"file_name":"src\\main.rs","byte_start":3942,"byte_end":3945,"line_start":140,"line_end":140,"column_start":28,"column_end":31},"ref_id":{"krate":0,"index":4060086295}},{"kind":"Variable","span":{"file_name":"src\\main.rs","byte_start":3950,"byte_end":3953,"line_start":140,"line_end":140,"column_start":36,"column_end":39},"ref_id":{"krate":0,"index":4060086295}},{"kind":"Function","span":{"file_name":"src\\main.rs","byte_start":3968,"byte_end":3980,"line_start":141,"line_end":141,"column_start":9,"column_end":21},"ref_id":{"krate":0,"index":19}},{"kind":"Variable","span":{"file_name":"src\\main.rs","byte_start":3981,"byte_end":3992,"line_start":141,"line_end":141,"column_start":22,"column_end":33},"ref_id":{"krate":0,"index":1073741847}},{"kind":"Variable","span":{"file_name":"src\\main.rs","byte_start":4040,"byte_end":4043,"line_start":143,"line_end":143,"column_start":9,"column_end":12},"ref_id":{"krate":0,"index":4060086295}},{"kind":"Type","span":{"file_name":"src\\main.rs","byte_start":4082,"byte_end":4086,"line_start":147,"line_end":147,"column_start":30,"column_end":34},"ref_id":{"krate":0,"index":45}},{"kind":"Type","span":{"file_name":"src\\main.rs","byte_start":4110,"byte_end":4114,"line_start":147,"line_end":147,"column_start":58,"column_end":62},"ref_id":{"krate":0,"index":45}},{"kind":"Type","span":{"file_name":"src\\main.rs","byte_start":4192,"byte_end":4196,"line_start":149,"line_end":149,"column_start":14,"column_end":18},"ref_id":{"krate":2,"index":44482}},{"kind":"Variable","span":{"file_name":"src\\main.rs","byte_start":4192,"byte_end":4193,"line_start":149,"line_end":149,"column_start":14,"column_end":15},"ref_id":{"krate":2,"index":44484}},{"kind":"Variable","span":{"file_name":"src\\main.rs","byte_start":4195,"byte_end":4196,"line_start":149,"line_end":149,"column_start":17,"column_end":18},"ref_id":{"krate":2,"index":44485}},{"kind":"Type","span":{"file_name":"src\\main.rs","byte_start":4216,"byte_end":4220,"line_start":150,"line_end":150,"column_start":18,"column_end":22},"ref_id":{"krate":2,"index":44482}},{"kind":"Variable","span":{"file_name":"src\\main.rs","byte_start":4216,"byte_end":4217,"line_start":150,"line_end":150,"column_start":18,"column_end":19},"ref_id":{"krate":2,"index":44484}},{"kind":"Variable","span":{"file_name":"src\\main.rs","byte_start":4219,"byte_end":4220,"line_start":150,"line_end":150,"column_start":21,"column_end":22},"ref_id":{"krate":2,"index":44485}},{"kind":"Function","span":{"file_name":"src\\main.rs","byte_start":4238,"byte_end":4248,"line_start":151,"line_end":151,"column_start":16,"column_end":26},"ref_id":{"krate":0,"index":36}},{"kind":"Variable","span":{"file_name":"src\\main.rs","byte_start":4249,"byte_end":4254,"line_start":151,"line_end":151,"column_start":27,"column_end":32},"ref_id":{"krate":0,"index":1073741853}},{"kind":"Variable","span":{"file_name":"src\\main.rs","byte_start":4257,"byte_end":4258,"line_start":151,"line_end":151,"column_start":35,"column_end":36},"ref_id":{"krate":0,"index":67108893}},{"kind":"Variable","span":{"file_name":"src\\main.rs","byte_start":4260,"byte_end":4261,"line_start":151,"line_end":151,"column_start":38,"column_end":39},"ref_id":{"krate":0,"index":671088669}},{"kind":"Variable","span":{"file_name":"src\\main.rs","byte_start":4264,"byte_end":4276,"line_start":151,"line_end":151,"column_start":42,"column_end":54},"ref_id":{"krate":0,"index":536870941}},{"kind":"Variable","span":{"file_name":"src\\main.rs","byte_start":4296,"byte_end":4307,"line_start":152,"line_end":152,"column_start":17,"column_end":28},"ref_id":{"krate":0,"index":1879048221}},{"kind":"Variable","span":{"file_name":"src\\main.rs","byte_start":4308,"byte_end":4309,"line_start":152,"line_end":152,"column_start":29,"column_end":30},"ref_id":{"krate":0,"index":67108893}},{"kind":"Variable","span":{"file_name":"src\\main.rs","byte_start":4311,"byte_end":4312,"line_start":152,"line_end":152,"column_start":32,"column_end":33},"ref_id":{"krate":0,"index":671088669}},{"kind":"Variable","span":{"file_name":"src\\main.rs","byte_start":4356,"byte_end":4367,"line_start":156,"line_end":156,"column_start":5,"column_end":16},"ref_id":{"krate":0,"index":1879048221}},{"kind":"Type","span":{"file_name":"src\\main.rs","byte_start":4394,"byte_end":4398,"line_start":159,"line_end":159,"column_start":24,"column_end":28},"ref_id":{"krate":0,"index":45}},{"kind":"Type","span":{"file_name":"src\\main.rs","byte_start":4439,"byte_end":4443,"line_start":159,"line_end":159,"column_start":69,"column_end":73},"ref_id":{"krate":0,"index":45}},{"kind":"Variable","span":{"file_name":"src\\main.rs","byte_start":4462,"byte_end":4467,"line_start":160,"line_end":160,"column_start":8,"column_end":13},"ref_id":{"krate":0,"index":1073741860}},{"kind":"Variable","span":{"file_name":"src\\main.rs","byte_start":4468,"byte_end":4471,"line_start":160,"line_end":160,"column_start":14,"column_end":17},"ref_id":{"krate":0,"index":536870948}},{"kind":"Variable","span":{"file_name":"src\\main.rs","byte_start":4476,"byte_end":4479,"line_start":160,"line_end":160,"column_start":22,"column_end":25},"ref_id":{"krate":0,"index":536870948}},{"kind":"Type","span":{"file_name":"src\\main.rs","byte_start":4493,"byte_end":4498,"line_start":160,"line_end":160,"column_start":39,"column_end":44},"ref_id":{"krate":0,"index":46}},{"kind":"Type","span":{"file_name":"src\\main.rs","byte_start":4487,"byte_end":4491,"line_start":160,"line_end":160,"column_start":33,"column_end":37},"ref_id":{"krate":0,"index":45}},{"kind":"Function","span":{"file_name":"src\\main.rs","byte_start":4708,"byte_end":4712,"line_start":174,"line_end":174,"column_start":21,"column_end":25},"ref_id":{"krate":2,"index":11513}},{"kind":"Variable","span":{"file_name":"src\\main.rs","byte_start":4703,"byte_end":4707,"line_start":174,"line_end":174,"column_start":16,"column_end":20},"ref_id":{"krate":0,"index":33554468}},{"kind":"Variable","span":{"file_name":"src\\main.rs","byte_start":4778,"byte_end":4781,"line_start":177,"line_end":177,"column_start":21,"column_end":24},"ref_id":{"krate":0,"index":536870948}},{"kind":"Variable","span":{"file_name":"src\\main.rs","byte_start":4794,"byte_end":4797,"line_start":177,"line_end":177,"column_start":37,"column_end":40},"ref_id":{"krate":0,"index":2717909028}},{"kind":"Variable","span":{"file_name":"src\\main.rs","byte_start":4803,"byte_end":4807,"line_start":177,"line_end":177,"column_start":46,"column_end":50},"ref_id":{"krate":0,"index":4060086308}},{"kind":"Variable","span":{"file_name":"src\\main.rs","byte_start":4829,"byte_end":4832,"line_start":178,"line_end":178,"column_start":21,"column_end":24},"ref_id":{"krate":0,"index":536870948}},{"kind":"Variable","span":{"file_name":"src\\main.rs","byte_start":4845,"byte_end":4848,"line_start":178,"line_end":178,"column_start":37,"column_end":40},"ref_id":{"krate":0,"index":2717909028}},{"kind":"Variable","span":{"file_name":"src\\main.rs","byte_start":4854,"byte_end":4858,"line_start":178,"line_end":178,"column_start":46,"column_end":50},"ref_id":{"krate":0,"index":4060086308}},{"kind":"Function","span":{"file_name":"src\\main.rs","byte_start":4884,"byte_end":4892,"line_start":179,"line_end":179,"column_start":25,"column_end":33},"ref_id":{"krate":2,"index":3378}},{"kind":"Variable","span":{"file_name":"src\\main.rs","byte_start":4894,"byte_end":4895,"line_start":179,"line_end":179,"column_start":35,"column_end":36},"ref_id":{"krate":0,"index":2248146980}},{"kind":"Function","span":{"file_name":"src\\main.rs","byte_start":4925,"byte_end":4933,"line_start":180,"line_end":180,"column_start":29,"column_end":37},"ref_id":{"krate":2,"index":3378}},{"kind":"Variable","span":{"file_name":"src\\main.rs","byte_start":4935,"byte_end":4936,"line_start":180,"line_end":180,"column_start":39,"column_end":40},"ref_id":{"krate":0,"index":3456106532}},{"kind":"Variable","span":{"file_name":"src\\main.rs","byte_start":4957,"byte_end":4962,"line_start":181,"line_end":181,"column_start":20,"column_end":25},"ref_id":{"krate":0,"index":1073741860}},{"kind":"Variable","span":{"file_name":"src\\main.rs","byte_start":4963,"byte_end":4964,"line_start":181,"line_end":181,"column_start":26,"column_end":27},"ref_id":{"krate":0,"index":2248146980}},{"kind":"Variable","span":{"file_name":"src\\main.rs","byte_start":4975,"byte_end":4976,"line_start":181,"line_end":181,"column_start":38,"column_end":39},"ref_id":{"krate":0,"index":3456106532}},{"kind":"Type","span":{"file_name":"src\\main.rs","byte_start":4996,"byte_end":5001,"line_start":181,"line_end":181,"column_start":59,"column_end":64},"ref_id":{"krate":0,"index":46}},{"kind":"Type","span":{"file_name":"src\\main.rs","byte_start":4990,"byte_end":4994,"line_start":181,"line_end":181,"column_start":53,"column_end":57},"ref_id":{"krate":0,"index":45}},{"kind":"Variable","span":{"file_name":"src\\main.rs","byte_start":5022,"byte_end":5026,"line_start":182,"line_end":182,"column_start":21,"column_end":25},"ref_id":{"krate":0,"index":4060086308}},{"kind":"Variable","span":{"file_name":"src\\main.rs","byte_start":5035,"byte_end":5040,"line_start":182,"line_end":182,"column_start":34,"column_end":39},"ref_id":{"krate":0,"index":1073741860}},{"kind":"Variable","span":{"file_name":"src\\main.rs","byte_start":5041,"byte_end":5042,"line_start":182,"line_end":182,"column_start":40,"column_end":41},"ref_id":{"krate":0,"index":2248146980}},{"kind":"Variable","span":{"file_name":"src\\main.rs","byte_start":5053,"byte_end":5054,"line_start":182,"line_end":182,"column_start":52,"column_end":53},"ref_id":{"krate":0,"index":3456106532}},{"kind":"Function","span":{"file_name":"src\\main.rs","byte_start":5081,"byte_end":5089,"line_start":182,"line_end":182,"column_start":80,"column_end":88},"ref_id":{"krate":0,"index":6}},{"kind":"Variable","span":{"file_name":"src\\main.rs","byte_start":5068,"byte_end":5080,"line_start":182,"line_end":182,"column_start":67,"column_end":79},"ref_id":{"krate":0,"index":1610612772}},{"kind":"Variable","span":{"file_name":"src\\main.rs","byte_start":5152,"byte_end":5157,"line_start":185,"line_end":185,"column_start":23,"column_end":28},"ref_id":{"krate":0,"index":1073741860}},{"kind":"Variable","span":{"file_name":"src\\main.rs","byte_start":5158,"byte_end":5159,"line_start":185,"line_end":185,"column_start":29,"column_end":30},"ref_id":{"krate":0,"index":2248146980}},{"kind":"Variable","span":{"file_name":"src\\main.rs","byte_start":5170,"byte_end":5171,"line_start":185,"line_end":185,"column_start":41,"column_end":42},"ref_id":{"krate":0,"index":3456106532}},{"kind":"Variable","span":{"file_name":"src\\main.rs","byte_start":5185,"byte_end":5197,"line_start":185,"line_end":185,"column_start":56,"column_end":68},"ref_id":{"krate":0,"index":1610612772}},{"kind":"Variable","span":{"file_name":"src\\main.rs","byte_start":5255,"byte_end":5259,"line_start":188,"line_end":188,"column_start":13,"column_end":17},"ref_id":{"krate":0,"index":4060086308}},{"kind":"Type","span":{"file_name":"src\\main.rs","byte_start":5324,"byte_end":5328,"line_start":194,"line_end":194,"column_start":30,"column_end":34},"ref_id":{"krate":0,"index":45}},{"kind":"Type","span":{"file_name":"src\\main.rs","byte_start":5369,"byte_end":5373,"line_start":194,"line_end":194,"column_start":75,"column_end":79},"ref_id":{"krate":0,"index":45}},{"kind":"Variable","span":{"file_name":"src\\main.rs","byte_start":5431,"byte_end":5443,"line_start":196,"line_end":196,"column_start":29,"column_end":41},"ref_id":{"krate":0,"index":1610612776}},{"kind":"Variable","span":{"file_name":"src\\main.rs","byte_start":5407,"byte_end":5412,"line_start":196,"line_end":196,"column_start":5,"column_end":10},"ref_id":{"krate":0,"index":1073741864}},{"kind":"Variable","span":{"file_name":"src\\main.rs","byte_start":5413,"byte_end":5416,"line_start":196,"line_end":196,"column_start":11,"column_end":14},"ref_id":{"krate":0,"index":536870952}},{"kind":"Variable","span":{"file_name":"src\\main.rs","byte_start":5421,"byte_end":5424,"line_start":196,"line_end":196,"column_start":19,"column_end":22},"ref_id":{"krate":0,"index":536870952}},{"kind":"Function","span":{"file_name":"src\\main.rs","byte_start":5623,"byte_end":5627,"line_start":207,"line_end":207,"column_start":21,"column_end":25},"ref_id":{"krate":2,"index":11513}},{"kind":"Variable","span":{"file_name":"src\\main.rs","byte_start":5618,"byte_end":5622,"line_start":207,"line_end":207,"column_start":16,"column_end":20},"ref_id":{"krate":0,"index":469762088}},{"kind":"Variable","span":{"file_name":"src\\main.rs","byte_start":5724,"byte_end":5727,"line_start":211,"line_end":211,"column_start":21,"column_end":24},"ref_id":{"krate":0,"index":536870952}},{"kind":"Variable","span":{"file_name":"src\\main.rs","byte_start":5740,"byte_end":5743,"line_start":211,"line_end":211,"column_start":37,"column_end":40},"ref_id":{"krate":0,"index":3154116648}},{"kind":"Variable","span":{"file_name":"src\\main.rs","byte_start":5749,"byte_end":5753,"line_start":211,"line_end":211,"column_start":46,"column_end":50},"ref_id":{"krate":0,"index":3791650856}},{"kind":"Variable","span":{"file_name":"src\\main.rs","byte_start":5775,"byte_end":5778,"line_start":212,"line_end":212,"column_start":21,"column_end":24},"ref_id":{"krate":0,"index":536870952}},{"kind":"Variable","span":{"file_name":"src\\main.rs","byte_start":5791,"byte_end":5794,"line_start":212,"line_end":212,"column_start":37,"column_end":40},"ref_id":{"krate":0,"index":3154116648}},{"kind":"Variable","span":{"file_name":"src\\main.rs","byte_start":5800,"byte_end":5804,"line_start":212,"line_end":212,"column_start":46,"column_end":50},"ref_id":{"krate":0,"index":3791650856}},{"kind":"Function","span":{"file_name":"src\\main.rs","byte_start":5830,"byte_end":5838,"line_start":213,"line_end":213,"column_start":25,"column_end":33},"ref_id":{"krate":2,"index":3378}},{"kind":"Variable","span":{"file_name":"src\\main.rs","byte_start":5840,"byte_end":5841,"line_start":213,"line_end":213,"column_start":35,"column_end":36},"ref_id":{"krate":0,"index":3120562216}},{"kind":"Function","span":{"file_name":"src\\main.rs","byte_start":5871,"byte_end":5879,"line_start":214,"line_end":214,"column_start":29,"column_end":37},"ref_id":{"krate":2,"index":3378}},{"kind":"Variable","span":{"file_name":"src\\main.rs","byte_start":5881,"byte_end":5882,"line_start":214,"line_end":214,"column_start":39,"column_end":40},"ref_id":{"krate":0,"index":4127195176}},{"kind":"Variable","span":{"file_name":"src\\main.rs","byte_start":5904,"byte_end":5908,"line_start":215,"line_end":215,"column_start":21,"column_end":25},"ref_id":{"krate":0,"index":3791650856}},{"kind":"Variable","span":{"file_name":"src\\main.rs","byte_start":5917,"byte_end":5922,"line_start":215,"line_end":215,"column_start":34,"column_end":39},"ref_id":{"krate":0,"index":1073741864}},{"kind":"Variable","span":{"file_name":"src\\main.rs","byte_start":5923,"byte_end":5924,"line_start":215,"line_end":215,"column_start":40,"column_end":41},"ref_id":{"krate":0,"index":3120562216}},{"kind":"Variable","span":{"file_name":"src\\main.rs","byte_start":5935,"byte_end":5936,"line_start":215,"line_end":215,"column_start":52,"column_end":53},"ref_id":{"krate":0,"index":4127195176}},{"kind":"Function","span":{"file_name":"src\\main.rs","byte_start":5963,"byte_end":5971,"line_start":215,"line_end":215,"column_start":80,"column_end":88},"ref_id":{"krate":0,"index":6}},{"kind":"Variable","span":{"file_name":"src\\main.rs","byte_start":5950,"byte_end":5962,"line_start":215,"line_end":215,"column_start":67,"column_end":79},"ref_id":{"krate":0,"index":1610612776}},{"kind":"Variable","span":{"file_name":"src\\main.rs","byte_start":6034,"byte_end":6039,"line_start":218,"line_end":218,"column_start":23,"column_end":28},"ref_id":{"krate":0,"index":1073741864}},{"kind":"Variable","span":{"file_name":"src\\main.rs","byte_start":6040,"byte_end":6041,"line_start":218,"line_end":218,"column_start":29,"column_end":30},"ref_id":{"krate":0,"index":3120562216}},{"kind":"Variable","span":{"file_name":"src\\main.rs","byte_start":6052,"byte_end":6053,"line_start":218,"line_end":218,"column_start":41,"column_end":42},"ref_id":{"krate":0,"index":4127195176}},{"kind":"Variable","span":{"file_name":"src\\main.rs","byte_start":6067,"byte_end":6079,"line_start":218,"line_end":218,"column_start":56,"column_end":68},"ref_id":{"krate":0,"index":1610612776}},{"kind":"Variable","span":{"file_name":"src\\main.rs","byte_start":6098,"byte_end":6103,"line_start":219,"line_end":219,"column_start":17,"column_end":22},"ref_id":{"krate":0,"index":3523215400}},{"kind":"Variable","span":{"file_name":"src\\main.rs","byte_start":6161,"byte_end":6165,"line_start":222,"line_end":222,"column_start":13,"column_end":17},"ref_id":{"krate":0,"index":3791650856}},{"kind":"Variable","span":{"file_name":"src\\main.rs","byte_start":6193,"byte_end":6198,"line_start":224,"line_end":224,"column_start":12,"column_end":17},"ref_id":{"krate":0,"index":3523215400}},{"kind":"Type","span":{"file_name":"src\\main.rs","byte_start":6222,"byte_end":6229,"line_start":225,"line_end":225,"column_start":22,"column_end":29},"ref_id":{"krate":2,"index":44482}},{"kind":"Variable","span":{"file_name":"src\\main.rs","byte_start":6222,"byte_end":6223,"line_start":225,"line_end":225,"column_start":22,"column_end":23},"ref_id":{"krate":2,"index":44484}},{"kind":"Variable","span":{"file_name":"src\\main.rs","byte_start":6225,"byte_end":6229,"line_start":225,"line_end":225,"column_start":25,"column_end":29},"ref_id":{"krate":2,"index":44485}},{"kind":"Variable","span":{"file_name":"src\\main.rs","byte_start":6225,"byte_end":6229,"line_start":225,"line_end":225,"column_start":25,"column_end":29},"ref_id":{"krate":0,"index":3791650856}},{"kind":"Variable","span":{"file_name":"src\\main.rs","byte_start":6256,"byte_end":6259,"line_start":226,"line_end":226,"column_start":25,"column_end":28},"ref_id":{"krate":0,"index":536870952}},{"kind":"Variable","span":{"file_name":"src\\main.rs","byte_start":6272,"byte_end":6275,"line_start":226,"line_end":226,"column_start":41,"column_end":44},"ref_id":{"krate":0,"index":3154116648}},{"kind":"Variable","span":{"file_name":"src\\main.rs","byte_start":6281,"byte_end":6282,"line_start":226,"line_end":226,"column_start":50,"column_end":51},"ref_id":{"krate":0,"index":1258291240}},{"kind":"Variable","span":{"file_name":"src\\main.rs","byte_start":6308,"byte_end":6311,"line_start":227,"line_end":227,"column_start":25,"column_end":28},"ref_id":{"krate":0,"index":536870952}},{"kind":"Variable","span":{"file_name":"src\\main.rs","byte_start":6324,"byte_end":6327,"line_start":227,"line_end":227,"column_start":41,"column_end":44},"ref_id":{"krate":0,"index":3154116648}},{"kind":"Variable","span":{"file_name":"src\\main.rs","byte_start":6333,"byte_end":6334,"line_start":227,"line_end":227,"column_start":50,"column_end":51},"ref_id":{"krate":0,"index":1258291240}},{"kind":"Variable","span":{"file_name":"src\\main.rs","byte_start":6384,"byte_end":6396,"line_start":228,"line_end":228,"column_start":49,"column_end":61},"ref_id":{"krate":0,"index":1610612776}},{"kind":"Variable","span":{"file_name":"src\\main.rs","byte_start":6352,"byte_end":6357,"line_start":228,"line_end":228,"column_start":17,"column_end":22},"ref_id":{"krate":0,"index":1073741864}},{"kind":"Variable","span":{"file_name":"src\\main.rs","byte_start":6358,"byte_end":6359,"line_start":228,"line_end":228,"column_start":23,"column_end":24},"ref_id":{"krate":0,"index":1459617832}},{"kind":"Variable","span":{"file_name":"src\\main.rs","byte_start":6370,"byte_end":6371,"line_start":228,"line_end":228,"column_start":35,"column_end":36},"ref_id":{"krate":0,"index":1056964648}},{"kind":"Function","span":{"file_name":"src\\main.rs","byte_start":6463,"byte_end":6475,"line_start":235,"line_end":235,"column_start":21,"column_end":33},"ref_id":{"krate":0,"index":8}},{"kind":"Type","span":{"file_name":"src\\main.rs","byte_start":6546,"byte_end":6551,"line_start":237,"line_end":237,"column_start":34,"column_end":39},"ref_id":{"krate":0,"index":48}},{"kind":"Type","span":{"file_name":"src\\main.rs","byte_start":6540,"byte_end":6544,"line_start":237,"line_end":237,"column_start":28,"column_end":32},"ref_id":{"krate":0,"index":45}},{"kind":"Function","span":{"file_name":"src\\main.rs","byte_start":6630,"byte_end":6646,"line_start":241,"line_end":241,"column_start":27,"column_end":43},"ref_id":{"krate":0,"index":29}},{"kind":"Variable","span":{"file_name":"src\\main.rs","byte_start":6647,"byte_end":6652,"line_start":241,"line_end":241,"column_start":44,"column_end":49},"ref_id":{"krate":0,"index":1610612780}},{"kind":"Variable","span":{"file_name":"src\\main.rs","byte_start":6654,"byte_end":6666,"line_start":241,"line_end":241,"column_start":51,"column_end":63},"ref_id":{"krate":0,"index":805306412}},{"kind":"Function","span":{"file_name":"src\\main.rs","byte_start":6677,"byte_end":6687,"line_start":242,"line_end":242,"column_start":9,"column_end":19},"ref_id":{"krate":0,"index":13}},{"kind":"Variable","span":{"file_name":"src\\main.rs","byte_start":6688,"byte_end":6693,"line_start":242,"line_end":242,"column_start":20,"column_end":25},"ref_id":{"krate":0,"index":1610612780}},{"kind":"Variable","span":{"file_name":"src\\main.rs","byte_start":6695,"byte_end":6706,"line_start":242,"line_end":242,"column_start":27,"column_end":38},"ref_id":{"krate":0,"index":1744830508}},{"kind":"Variable","span":{"file_name":"src\\main.rs","byte_start":6708,"byte_end":6720,"line_start":242,"line_end":242,"column_start":40,"column_end":52},"ref_id":{"krate":0,"index":805306412}},{"kind":"Function","span":{"file_name":"src\\main.rs","byte_start":6743,"byte_end":6752,"line_start":243,"line_end":243,"column_start":21,"column_end":30},"ref_id":{"krate":0,"index":23}},{"kind":"Variable","span":{"file_name":"src\\main.rs","byte_start":6753,"byte_end":6764,"line_start":243,"line_end":243,"column_start":31,"column_end":42},"ref_id":{"krate":0,"index":1744830508}},{"kind":"Function","span":{"file_name":"src\\main.rs","byte_start":6775,"byte_end":6786,"line_start":244,"line_end":244,"column_start":9,"column_end":20},"ref_id":{"krate":0,"index":40}},{"kind":"Variable","span":{"file_name":"src\\main.rs","byte_start":6792,"byte_end":6797,"line_start":244,"line_end":244,"column_start":26,"column_end":31},"ref_id":{"krate":0,"index":1610612780}},{"kind":"Variable","span":{"file_name":"src\\main.rs","byte_start":6799,"byte_end":6804,"line_start":244,"line_end":244,"column_start":33,"column_end":38},"ref_id":{"krate":0,"index":335544364}},{"kind":"Variable","span":{"file_name":"src\\main.rs","byte_start":6806,"byte_end":6818,"line_start":244,"line_end":244,"column_start":40,"column_end":52},"ref_id":{"krate":0,"index":805306412}},{"kind":"Function","span":{"file_name":"src\\main.rs","byte_start":6858,"byte_end":6866,"line_start":246,"line_end":246,"column_start":37,"column_end":45},"ref_id":{"krate":0,"index":6}},{"kind":"Variable","span":{"file_name":"src\\main.rs","byte_start":6845,"byte_end":6857,"line_start":246,"line_end":246,"column_start":24,"column_end":36},"ref_id":{"krate":0,"index":805306412}},{"kind":"Variable","span":{"file_name":"src\\main.rs","byte_start":6830,"byte_end":6842,"line_start":246,"line_end":246,"column_start":9,"column_end":21},"ref_id":{"krate":0,"index":805306412}}],"macro_refs":[],"relations":[{"span":{"file_name":"src\\main.rs","byte_start":112,"byte_end":116,"line_start":9,"line_end":9,"column_start":6,"column_end":10},"kind":{"Impl":{"id":0}},"from":{"krate":0,"index":45},"to":{"krate":4294967295,"index":4294967295}}]}